docking_eval/__init__.py
docking_eval-0.8.dist-info/LICENSE
docking_eval-0.8.dist-info/METADATA
docking_eval-0.8.dist-info/WHEEL
docking_eval-0.8.dist-info/top_level.txt
docking_eval-0.8.dist-info/RECORD
